{
  "openapi": "3.0.1",
  "info": {
    "title": "API_Institucion",
    "version": "1.0"
  },
  "paths": {
    "/api/AuthAdministrador/login": {
      "post": {
        "tags": [
          "AuthAdministrador"
        ],
        "requestBody": {
          "content": {
            "application/json": {
              "schema": {
                "$ref": "#/components/schemas/Login"
              }
            },
            "text/json": {
              "schema": {
                "$ref": "#/components/schemas/Login"
              }
            },
            "application/*+json": {
              "schema": {
                "$ref": "#/components/schemas/Login"
              }
            }
          }
        },
        "responses": {
          "200": {
            "description": "OK"
          }
        }
      }
    },
    "/api/AuthAdministrador/registrar": {
      "post": {
        "tags": [
          "AuthAdministrador"
        ],
        "requestBody": {
          "content": {
            "application/json": {
              "schema": {
                "$ref": "#/components/schemas/AdministradorDto"
              }
            },
            "text/json": {
              "schema": {
                "$ref": "#/components/schemas/AdministradorDto"
              }
            },
            "application/*+json": {
              "schema": {
                "$ref": "#/components/schemas/AdministradorDto"
              }
            }
          }
        },
        "responses": {
          "200": {
            "description": "OK"
          }
        }
      }
    },
    "/api/AuthAlumno/login": {
      "post": {
        "tags": [
          "AuthAlumno"
        ],
        "requestBody": {
          "content": {
            "application/json": {
              "schema": {
                "$ref": "#/components/schemas/Login"
              }
            },
            "text/json": {
              "schema": {
                "$ref": "#/components/schemas/Login"
              }
            },
            "application/*+json": {
              "schema": {
                "$ref": "#/components/schemas/Login"
              }
            }
          }
        },
        "responses": {
          "200": {
            "description": "OK"
          }
        }
      }
    },
    "/api/AuthAlumno/registrar": {
      "post": {
        "tags": [
          "AuthAlumno"
        ],
        "requestBody": {
          "content": {
            "application/json": {
              "schema": {
                "$ref": "#/components/schemas/UsuarioDto"
              }
            },
            "text/json": {
              "schema": {
                "$ref": "#/components/schemas/UsuarioDto"
              }
            },
            "application/*+json": {
              "schema": {
                "$ref": "#/components/schemas/UsuarioDto"
              }
            }
          }
        },
        "responses": {
          "200": {
            "description": "OK"
          }
        }
      }
    },
    "/api/AuthProfesor/login": {
      "post": {
        "tags": [
          "AuthProfesor"
        ],
        "requestBody": {
          "content": {
            "application/json": {
              "schema": {
                "$ref": "#/components/schemas/Login"
              }
            },
            "text/json": {
              "schema": {
                "$ref": "#/components/schemas/Login"
              }
            },
            "application/*+json": {
              "schema": {
                "$ref": "#/components/schemas/Login"
              }
            }
          }
        },
        "responses": {
          "200": {
            "description": "OK"
          }
        }
      }
    },
    "/api/AuthProfesor/registrar": {
      "post": {
        "tags": [
          "AuthProfesor"
        ],
        "requestBody": {
          "content": {
            "application/json": {
              "schema": {
                "$ref": "#/components/schemas/UsuarioDto"
              }
            },
            "text/json": {
              "schema": {
                "$ref": "#/components/schemas/UsuarioDto"
              }
            },
            "application/*+json": {
              "schema": {
                "$ref": "#/components/schemas/UsuarioDto"
              }
            }
          }
        },
        "responses": {
          "200": {
            "description": "OK"
          }
        }
      }
    },
    "/api/Carreras": {
      "get": {
        "tags": [
          "Carreras"
        ],
        "responses": {
          "200": {
            "description": "OK"
          }
        }
      }
    },
    "/api/Carreras/{id}": {
      "get": {
        "tags": [
          "Carreras"
        ],
        "parameters": [
          {
            "name": "id",
            "in": "path",
            "required": true,
            "schema": {
              "type": "integer",
              "format": "int32"
            }
          }
        ],
        "responses": {
          "200": {
            "description": "OK"
          }
        }
      }
    },
    "/api/Usuario/materias": {
      "post": {
        "tags": [
          "Usuario"
        ],
        "parameters": [
          {
            "name": "token",
            "in": "query",
            "schema": {
              "type": "string"
            }
          }
        ],
        "requestBody": {
          "content": {
            "application/json": {
              "schema": {
                "type": "array",
                "items": {
                  "$ref": "#/components/schemas/MateriaDto"
                }
              }
            },
            "text/json": {
              "schema": {
                "type": "array",
                "items": {
                  "$ref": "#/components/schemas/MateriaDto"
                }
              }
            },
            "application/*+json": {
              "schema": {
                "type": "array",
                "items": {
                  "$ref": "#/components/schemas/MateriaDto"
                }
              }
            }
          }
        },
        "responses": {
          "200": {
            "description": "OK"
          }
        }
      }
    },
    "/WeatherForecast": {
      "get": {
        "tags": [
          "WeatherForecast"
        ],
        "operationId": "GetWeatherForecast",
        "responses": {
          "200": {
            "description": "OK",
            "content": {
              "text/plain": {
                "schema": {
                  "type": "array",
                  "items": {
                    "$ref": "#/components/schemas/WeatherForecast"
                  }
                }
              },
              "application/json": {
                "schema": {
                  "type": "array",
                  "items": {
                    "$ref": "#/components/schemas/WeatherForecast"
                  }
                }
              },
              "text/json": {
                "schema": {
                  "type": "array",
                  "items": {
                    "$ref": "#/components/schemas/WeatherForecast"
                  }
                }
              }
            }
          }
        }
      }
    }
  },
  "components": {
    "schemas": {
      "AdministradorDto": {
        "type": "object",
        "properties": {
          "rol": {
            "type": "integer",
            "format": "int32"
          },
          "dni": {
            "type": "string",
            "nullable": true
          },
          "nombre": {
            "type": "string",
            "nullable": true
          },
          "email": {
            "type": "string",
            "nullable": true
          },
          "departamento": {
            "type": "string",
            "nullable": true
          },
          "password": {
            "type": "string",
            "nullable": true
          }
        },
        "additionalProperties": false
      },
      "Login": {
        "type": "object",
        "properties": {
          "dni": {
            "type": "string",
            "nullable": true
          },
          "password": {
            "type": "string",
            "nullable": true
          }
        },
        "additionalProperties": false
      },
      "MateriaDto": {
        "type": "object",
        "additionalProperties": false
      },
      "UsuarioDto": {
        "type": "object",
        "properties": {
          "rol": {
            "type": "integer",
            "format": "int32"
          },
          "dni": {
            "type": "string",
            "nullable": true
          },
          "nombre": {
            "type": "string",
            "nullable": true
          },
          "email": {
            "type": "string",
            "nullable": true
          },
          "departamento": {
            "type": "string",
            "nullable": true
          },
          "password": {
            "type": "string",
            "nullable": true
          }
        },
        "additionalProperties": false
      },
      "WeatherForecast": {
        "type": "object",
        "properties": {
          "date": {
            "type": "string",
            "format": "date"
          },
          "temperatureC": {
            "type": "integer",
            "format": "int32"
          },
          "temperatureF": {
            "type": "integer",
            "format": "int32",
            "readOnly": true
          },
          "summary": {
            "type": "string",
            "nullable": true
          }
        },
        "additionalProperties": false
      }
    }
  }
}